{
  "version": "7",
  "dialect": "postgresql",
  "entries": [
    {
      "idx": 0,
      "version": "7",
      "when": 1761736693451,
      "tag": "0000_pale_nitro",
      "breakpoints": true
    },
    {
      "idx": 1,
      "version": "7",
      "when": 1761737450570,
      "tag": "0001_aromatic_scorpion",
      "breakpoints": true
    },
    {
      "idx": 2,
      "version": "7",
      "when": 1761739510427,
      "tag": "0002_many_kitty_pryde",
      "breakpoints": true
    },
    {
      "idx": 3,
      "version": "7",
      "when": 1761777119403,
      "tag": "0003_wet_garia",
      "breakpoints": true
    },
    {
      "idx": 4,
      "version": "7",
      "when": 1761777222932,
      "tag": "0004_steep_captain_stacy",
      "breakpoints": true
    },
    {
      "idx": 5,
      "version": "7",
      "when": 1764759478907,
      "tag": "0005_fluffy_harpoon",
      "breakpoints": true
    }
  ]
}